{"data_mtime":1741162450,"dep_lines":[6,7,5,11,15,1,3,5,10,12,1,1,1,1,1,1,1,1,1,1,1,1,1,1,1,1,1,1,1,1,1],"dep_prios":[5,5,10,25,25,5,5,20,25,25,5,30,30,30,30,30,30,30,30,30,30,30,30,30,30,30,30,30,30,30,30],"dependencies":["polars._utils.convert","polars._utils.deprecation","polars.functions","collections.abc","polars._typing","__future__","typing","polars","sys","datetime","builtins","_frozen_importlib","_typeshed","abc","decimal","polars._utils","polars.dataframe.frame","polars.datatypes","polars.datatypes.classes","polars.expr","polars.expr.expr","polars.functions.aggregation","polars.functions.aggregation.vertical","polars.functions.lazy","polars.lazyframe","polars.lazyframe.engine_config","polars.lazyframe.frame","polars.lazyframe.group_by","polars.lazyframe.in_process","polars.series","polars.series.series"],"hash":"f24f4ea0b88a95b8564aa68fa85f5d100113613d","id":"polars.dataframe.group_by","ignore_all":true,"interface_hash":"4e8a1e8c97aa3e306e714babcf4629d12f68e19a","mtime":1741161225,"options":{"allow_redefinition":false,"allow_untyped_globals":false,"always_false":[],"always_true":[],"bazel":false,"check_untyped_defs":true,"disable_bytearray_promotion":false,"disable_error_code":[],"disable_memoryview_promotion":false,"disabled_error_codes":[],"disallow_any_decorated":false,"disallow_any_explicit":false,"disallow_any_expr":false,"disallow_any_generics":false,"disallow_any_unimported":false,"disallow_incomplete_defs":true,"disallow_subclassing_any":false,"disallow_untyped_calls":false,"disallow_untyped_decorators":true,"disallow_untyped_defs":true,"enable_error_code":[],"enabled_error_codes":[],"extra_checks":false,"follow_imports":"normal","follow_imports_for_stubs":false,"follow_untyped_imports":false,"ignore_errors":false,"ignore_missing_imports":true,"implicit_optional":false,"implicit_reexport":true,"local_partial_types":false,"mypyc":false,"old_type_inference":false,"platform":"linux","plugins":[],"strict_concatenate":false,"strict_equality":false,"strict_optional":true,"warn_no_return":true,"warn_return_any":true,"warn_unreachable":true,"warn_unused_ignores":true},"path":"/home/keisei/development/finance_app/services/lambda_data_fetcher/.venv/lib/python3.13/site-packages/polars/dataframe/group_by.py","plugin_data":null,"size":37867,"suppressed":[],"version_id":"1.14.1"}